tmux_tui/__init__.py
tmux_tui/main.py
tmux_tui-0.1.6.dist-info/METADATA
tmux_tui-0.1.6.dist-info/WHEEL
tmux_tui-0.1.6.dist-info/entry_points.txt
tmux_tui-0.1.6.dist-info/RECORD
